CHANGES.txt
MANIFEST.in
README.txt
RELEASE
setup.cfg
setup.py
niteoweb/__init__.py
niteoweb.windmill.egg-info/PKG-INFO
niteoweb.windmill.egg-info/SOURCES.txt
niteoweb.windmill.egg-info/dependency_links.txt
niteoweb.windmill.egg-info/namespace_packages.txt
niteoweb.windmill.egg-info/not-zip-safe
niteoweb.windmill.egg-info/requires.txt
niteoweb.windmill.egg-info/top_level.txt
niteoweb/windmill/__init__.py
niteoweb/windmill/zserver.py
niteoweb/windmill/tests/__init__.py
niteoweb/windmill/tests/test_windmill.py