Metadata-Version: 1.0
Name: niteoweb.windmill
Version: 0.3.2
Summary: Plone TestCase integration with Windmill testing
Home-page: http://www.niteoweb.com/
Author: Niteoweb d.o.o.
Author-email: info@niteoweb.com
License: GNU GPL
Keywords: zope plone windmill
Platform: UNKNOWN
Classifier: Framework :: Plone
Classifier: Framework :: Zope2
Classifier: Framework :: Zope3
Classifier: Programming Language :: Python
Classifier: Topic :: Software Development :: Libraries :: Python Modules
